django_json_messages-0.1.2.dist-info/DESCRIPTION.rst
django_json_messages-0.1.2.dist-info/entry_points.txt
django_json_messages-0.1.2.dist-info/METADATA
django_json_messages-0.1.2.dist-info/metadata.json
django_json_messages-0.1.2.dist-info/RECORD
django_json_messages-0.1.2.dist-info/top_level.txt
django_json_messages-0.1.2.dist-info/WHEEL
json_messages/__init__.py
json_messages/context_processors.py
json_messages/templatetags/__init__.py
json_messages/templatetags/json_messages.py
