Metadata-Version: 2.0
Name: django-json-messages
Version: 0.1.2
Summary: Json encode messages from the Django messages framework and dump them as JS
Home-page: https://github.com/matiboy/django-json-messages.git
Author: Matiboy
Author-email: mathieu@redapesolutions.com
License: GPLv2
Keywords: django messages framework json
Platform: UNKNOWN
Classifier: Development Status :: 3 - Alpha
Classifier: Intended Audience :: Developers
Classifier: Framework :: Django
Classifier: License :: OSI Approved :: MIT License
Classifier: Programming Language :: Python :: 2
Classifier: Programming Language :: Python :: 2.6
Classifier: Programming Language :: Python :: 2.7
Classifier: Programming Language :: Python :: 3
Classifier: Programming Language :: Python :: 3.2
Classifier: Programming Language :: Python :: 3.3
Classifier: Programming Language :: Python :: 3.4
Provides-Extra: test
Requires-Dist: coverage; extra == 'test'
Provides-Extra: dev
Requires-Dist: check-manifest; extra == 'dev'
